MedicalImageConverter/__init__.py
MedicalImageConverter/memory.py
MedicalImageConverter/reader.py
MedicalImageConverter/Data/__init__.py
MedicalImageConverter/Data/deformable.py
MedicalImageConverter/Data/dose.py
MedicalImageConverter/Data/image.py
MedicalImageConverter/Data/poi.py
MedicalImageConverter/Data/rigid.py
MedicalImageConverter/Data/roi.py
MedicalImageConverter/Read/__init__.py
MedicalImageConverter/Read/dicom.py
MedicalImageConverter/Read/mf3.py
MedicalImageConverter/Read/mhd.py
MedicalImageConverter/Read/nifti.py
MedicalImageConverter/Read/stl.py
MedicalImageConverter/Read/vtk.py
MedicalImageConverter/Utils/__init__.py
MedicalImageConverter/Utils/conversion.py
MedicalImageConverter/Utils/creation.py
MedicalImageConverter/Utils/Mesh/__init__.py
MedicalImageConverter/Utils/Mesh/surface.py
MedicalImageConverter/Utils/Mesh/volume.py
medicalimageconverter-2.1.73.dist-info/LICENSE.txt
medicalimageconverter-2.1.73.dist-info/METADATA
medicalimageconverter-2.1.73.dist-info/WHEEL
medicalimageconverter-2.1.73.dist-info/top_level.txt
medicalimageconverter-2.1.73.dist-info/RECORD
