Metadata-Version: 2.1
Name: medicalimageconverter
Version: 2.1.73
Summary: Reads in medical images and structures them into 3D arrays with associated ROI/POIs if they exist.
Home-page: https://github.com/caleb-oconnor/MedicalImageConverter
Author: Caleb OConnor
Author-email: csoconnor@mdanderson.org
Classifier: Programming Language :: Python :: 3
Classifier: License :: OSI Approved :: GNU Affero General Public License v3
License-File: LICENSE.txt
Requires-Dist: asttokens==3.0.0
Requires-Dist: attrs==25.1.0
Requires-Dist: backcall==0.2.0
Requires-Dist: beautifulsoup4==4.13.3
Requires-Dist: bleach==6.2.0
Requires-Dist: certifi==2025.1.31
Requires-Dist: charset-normalizer==3.4.1
Requires-Dist: colorama==0.4.6
Requires-Dist: contourpy==1.3.1
Requires-Dist: cycler==0.12.1
Requires-Dist: decorator==5.2.1
Requires-Dist: defusedxml==0.7.1
Requires-Dist: docopt==0.6.2
Requires-Dist: executing==2.2.0
Requires-Dist: fastjsonschema==2.21.1
Requires-Dist: fonttools==4.56.0
Requires-Dist: idna==3.10
Requires-Dist: importlib-resources==6.5.2
Requires-Dist: ipython==8.12.3
Requires-Dist: jedi==0.19.2
Requires-Dist: Jinja2==3.1.6
Requires-Dist: jsonschema==4.23.0
Requires-Dist: jsonschema-specifications==2024.10.1
Requires-Dist: jupyter-client==8.6.3
Requires-Dist: jupyter-core==5.7.2
Requires-Dist: jupyterlab-pygments==0.3.0
Requires-Dist: kiwisolver==1.4.8
Requires-Dist: MarkupSafe==3.0.2
Requires-Dist: matplotlib==3.10.1
Requires-Dist: matplotlib-inline==0.1.7
Requires-Dist: mistune==3.1.2
Requires-Dist: nbclient==0.10.2
Requires-Dist: nbconvert==7.16.6
Requires-Dist: nbformat==5.10.4
Requires-Dist: nibabel==5.3.2
Requires-Dist: numpy==2.2.3
Requires-Dist: opencv-python==4.11.0.86
Requires-Dist: packaging==24.2
Requires-Dist: pandas==2.2.3
Requires-Dist: pandocfilters==1.5.1
Requires-Dist: parso==0.8.4
Requires-Dist: pickleshare==0.7.5
Requires-Dist: pillow==11.1.0
Requires-Dist: pipreqs==0.5.0
Requires-Dist: platformdirs==4.3.6
Requires-Dist: pooch==1.8.2
Requires-Dist: prompt-toolkit==3.0.50
Requires-Dist: psutil==7.0.0
Requires-Dist: pure-eval==0.2.3
Requires-Dist: pyacvd==0.3.1
Requires-Dist: pydicom==3.0.1
Requires-Dist: Pygments==2.19.1
Requires-Dist: pykdtree==1.4.1
Requires-Dist: pyparsing==3.2.1
Requires-Dist: pytetwild==0.1.dev1
Requires-Dist: python-dateutil==2.9.0.post0
Requires-Dist: python-gdcm==3.0.24.1
Requires-Dist: pytz==2025.1
Requires-Dist: pyvista==0.44.2
Requires-Dist: pywin32==308
Requires-Dist: pyzmq==26.2.1
Requires-Dist: referencing==0.36.2
Requires-Dist: requests==2.32.3
Requires-Dist: rpds-py==0.23.1
Requires-Dist: scipy==1.15.2
Requires-Dist: scooby==0.10.0
Requires-Dist: SimpleITK==2.4.1
Requires-Dist: six==1.17.0
Requires-Dist: soupsieve==2.6
Requires-Dist: stack-data==0.6.3
Requires-Dist: tinycss2==1.4.0
Requires-Dist: tornado==6.4.2
Requires-Dist: traitlets==5.14.3
Requires-Dist: typing-extensions==4.12.2
Requires-Dist: tzdata==2025.1
Requires-Dist: urllib3==2.3.0
Requires-Dist: vtk==9.3.1
Requires-Dist: wcwidth==0.2.13
Requires-Dist: webencodings==0.5.1
Requires-Dist: yarg==0.1.9
